README.md
setup.py
edge_impulse_sdk/__init__.py
edge_impulse_sdk/api_client.py
edge_impulse_sdk/configuration.py
edge_impulse_sdk/exceptions.py
edge_impulse_sdk/rest.py
edge_impulse_sdk.egg-info/PKG-INFO
edge_impulse_sdk.egg-info/SOURCES.txt
edge_impulse_sdk.egg-info/dependency_links.txt
edge_impulse_sdk.egg-info/requires.txt
edge_impulse_sdk.egg-info/top_level.txt
edge_impulse_sdk/api/__init__.py
edge_impulse_sdk/api/admin_api.py
edge_impulse_sdk/api/allows_read_only_api.py
edge_impulse_sdk/api/auth_api.py
edge_impulse_sdk/api/cdn_api.py
edge_impulse_sdk/api/classify_api.py
edge_impulse_sdk/api/deployment_api.py
edge_impulse_sdk/api/devices_api.py
edge_impulse_sdk/api/dsp_api.py
edge_impulse_sdk/api/export_api.py
edge_impulse_sdk/api/health_api.py
edge_impulse_sdk/api/impulse_api.py
edge_impulse_sdk/api/jobs_api.py
edge_impulse_sdk/api/learn_api.py
edge_impulse_sdk/api/login_api.py
edge_impulse_sdk/api/optimization_api.py
edge_impulse_sdk/api/organization_blocks_api.py
edge_impulse_sdk/api/organization_create_project_api.py
edge_impulse_sdk/api/organization_data_api.py
edge_impulse_sdk/api/organization_jobs_api.py
edge_impulse_sdk/api/organization_portals_api.py
edge_impulse_sdk/api/organization_requires_admin_api.py
edge_impulse_sdk/api/organizations_api.py
edge_impulse_sdk/api/projects_api.py
edge_impulse_sdk/api/raw_data_api.py
edge_impulse_sdk/api/requires_sudo_api.py
edge_impulse_sdk/api/requires_third_party_auth_api_key_api.py
edge_impulse_sdk/api/supports_range_api.py
edge_impulse_sdk/api/third_party_auth_api.py
edge_impulse_sdk/api/upload_portal_api.py
edge_impulse_sdk/api/user_api.py
edge_impulse_sdk/models/__init__.py
edge_impulse_sdk/models/activate_user_by_third_party_activation_code_request.py
edge_impulse_sdk/models/activate_user_request.py
edge_impulse_sdk/models/add_api_key_request.py
edge_impulse_sdk/models/add_collaborator_request.py
edge_impulse_sdk/models/add_hmac_key_request.py
edge_impulse_sdk/models/add_member_request.py
edge_impulse_sdk/models/add_note_request.py
edge_impulse_sdk/models/add_organization_api_key_request.py
edge_impulse_sdk/models/add_organization_bucket_request.py
