Metadata-Version: 1.0
Name: edge-impulse-sdk
Version: 1.2.0
Summary: Edge Impulse API
Home-page: UNKNOWN
Author: UNKNOWN
Author-email: UNKNOWN
License: UNKNOWN
Keywords: OpenAPI,OpenAPI-Generator,Edge Impulse API
Platform: UNKNOWN
